<?xml version="1.0" encoding="UTF-8" ?>

<PMML
	version="4.3"
	xmlns="http://www.dmg.org/PMML-4_3"
	xmlns:xsi="http://www.w3.org/2001/XMLSchema-instance"
	xsi:schemaLocation="http://www.dmg.org/PMML-4_3 pmml-4-3.xsd">
	<Header
		copyright="Copyright (c) IBM Corp. 1989, 2017.">
		<Application
			name="IBM SPSS Statistics"
			version="26.0.0.0"/>
		<Timestamp>Sat Dec 03 14:45:33 2022</Timestamp>
	</Header>
	<DataDictionary
		numberOfFields="9">
		<DataField
			name="revenue"
			optype="continuous"
			dataType="double"/>
		<DataField
			name="tv_S"
			optype="continuous"
			dataType="double"/>
		<DataField
			name="ooh_S"
			optype="continuous"
			dataType="double"/>
		<DataField
			name="print_S"
			optype="continuous"
			dataType="double"/>
		<DataField
			name="search_S"
			optype="continuous"
			dataType="double"/>
		<DataField
			name="facebook_S"
			optype="continuous"
			dataType="double"/>
		<DataField
			name="facebook_I"
			optype="continuous"
			dataType="double"/>
		<DataField
			name="search_clicks_P"
			optype="continuous"
			dataType="double"/>
		<DataField
			name="competitor_sales_B"
			optype="continuous"
			dataType="double"/>
	</DataDictionary>
	<TransformationDictionary>
		<DerivedField
			optype="continuous"
			dataType="double"
			name="revenueNorm">
			<NormContinuous
				field="revenue">
				<LinearNorm
					orig="672250"
					norm="-1.624274650031"/>
				<LinearNorm
					orig="3827520"
					norm="2.80987407136209"/>
			</NormContinuous>
		</DerivedField>
		<DerivedField
			optype="continuous"
			dataType="double"
			name="tv_SNorm">
			<NormContinuous
				field="tv_S">
				<LinearNorm
					orig="0"
					norm="-0.527348126301058"/>
				<LinearNorm
					orig="1185349.3"
					norm="4.88377094396137"/>
			</NormContinuous>
		</DerivedField>
		<DerivedField
			optype="continuous"
			dataType="double"
			name="ooh_SNorm">
			<NormContinuous
				field="ooh_S">
				<LinearNorm
					orig="0"
					norm="-0.547106944861382"/>
				<LinearNorm
					orig="938178"
					norm="4.86943664793979"/>
			</NormContinuous>
		</DerivedField>
		<DerivedField
			optype="continuous"
			dataType="double"
			name="print_SNorm">
			<NormContinuous
				field="print_S">
				<LinearNorm
					orig="0"
					norm="-0.612721697231948"/>
				<LinearNorm
					orig="209986"
					norm="3.63020020690615"/>
			</NormContinuous>
		</DerivedField>
		<DerivedField
			optype="continuous"
			dataType="double"
			name="search_SNorm">
			<NormContinuous
				field="search_S">
				<LinearNorm
					orig="0"
					norm="-1.30489002375998"/>
				<LinearNorm
					orig="128600"
					norm="2.570973604691"/>
			</NormContinuous>
		</DerivedField>
		<DerivedField
			optype="continuous"
			dataType="double"
			name="facebook_SNorm">
			<NormContinuous
				field="facebook_S">
				<LinearNorm
					orig="0"
					norm="-0.700872309004717"/>
				<LinearNorm
					orig="417018.577"
					norm="3.86162534544995"/>
			</NormContinuous>
		</DerivedField>
		<DerivedField
			optype="continuous"
			dataType="double"
			name="facebook_INorm">
			<NormContinuous
				field="facebook_I">
				<LinearNorm
					orig="0"
					norm="-0.718444051301536"/>
				<LinearNorm
					orig="145985945.1"
					norm="3.56237594492749"/>
			</NormContinuous>
		</DerivedField>
		<DerivedField
			optype="continuous"
			dataType="double"
			name="search_clicks_PNorm">
			<NormContinuous
				field="search_clicks_P">
				<LinearNorm
					orig="0"
					norm="-1.30093763630107"/>
				<LinearNorm
					orig="156564.3846"
					norm="2.82071661606698"/>
			</NormContinuous>
		</DerivedField>
		<DerivedField
			optype="continuous"
			dataType="double"
			name="competitor_sales_BNorm">
			<NormContinuous
				field="competitor_sales_B">
				<LinearNorm
					orig="2240235"
					norm="-1.62538212301902"/>
				<LinearNorm
					orig="9984742"
					norm="2.12635609042296"/>
			</NormContinuous>
		</DerivedField>
	</TransformationDictionary>
	<NeuralNetwork
		functionName="regression"
		activationFunction="logistic">
		<MiningSchema>
			<MiningField
				name="tv_S"/>
			<MiningField
				name="ooh_S"/>
			<MiningField
				name="print_S"/>
			<MiningField
				name="search_S"/>
			<MiningField
				name="facebook_S"/>
			<MiningField
				name="facebook_I"/>
			<MiningField
				name="search_clicks_P"/>
			<MiningField
				name="competitor_sales_B"/>
			<MiningField
				name="revenue"
				usageType="predicted"/>
		</MiningSchema>
		<NeuralInputs>
			<NeuralInput
				id="0">
				<DerivedField
					optype="continuous"
					dataType="double">
					<FieldRef
						field="tv_SNorm"/>
				</DerivedField>
			</NeuralInput>
			<NeuralInput
				id="1">
				<DerivedField
					optype="continuous"
					dataType="double">
					<FieldRef
						field="ooh_SNorm"/>
				</DerivedField>
			</NeuralInput>
			<NeuralInput
				id="2">
				<DerivedField
					optype="continuous"
					dataType="double">
					<FieldRef
						field="print_SNorm"/>
				</DerivedField>
			</NeuralInput>
			<NeuralInput
				id="3">
				<DerivedField
					optype="continuous"
					dataType="double">
					<FieldRef
						field="search_SNorm"/>
				</DerivedField>
			</NeuralInput>
			<NeuralInput
				id="4">
				<DerivedField
					optype="continuous"
					dataType="double">
					<FieldRef
						field="facebook_SNorm"/>
				</DerivedField>
			</NeuralInput>
			<NeuralInput
				id="5">
				<DerivedField
					optype="continuous"
					dataType="double">
					<FieldRef
						field="facebook_INorm"/>
				</DerivedField>
			</NeuralInput>
			<NeuralInput
				id="6">
				<DerivedField
					optype="continuous"
					dataType="double">
					<FieldRef
						field="search_clicks_PNorm"/>
				</DerivedField>
			</NeuralInput>
			<NeuralInput
				id="7">
				<DerivedField
					optype="continuous"
					dataType="double">
					<FieldRef
						field="competitor_sales_BNorm"/>
				</DerivedField>
			</NeuralInput>
		</NeuralInputs>
		<NeuralLayer
			numberOfNeurons="8">
			<Neuron
				id="8"
				bias="0.40163287024603">
				<Con
					from="0"
					weight="-0.187375528459542"/>
				<Con
					from="1"
					weight="-0.164116876468113"/>
				<Con
					from="2"
					weight="-0.313515191630485"/>
				<Con
					from="3"
					weight="0.304877347795647"/>
				<Con
					from="4"
					weight="-0.408162705208775"/>
				<Con
					from="5"
					weight="-0.395369223113036"/>
				<Con
					from="6"
					weight="0.362298935712821"/>
				<Con
					from="7"
					weight="-0.198529734005244"/>
			</Neuron>
			<Neuron
				id="9"
				bias="-0.333126017049136">
				<Con
					from="0"
					weight="-0.140148831220124"/>
				<Con
					from="1"
					weight="-0.0667354969740249"/>
				<Con
					from="2"
					weight="0.495838230703127"/>
				<Con
					from="3"
					weight="0.0710073297905955"/>
				<Con
					from="4"
					weight="0.18207036624336"/>
				<Con
					from="5"
					weight="-0.196431615159054"/>
				<Con
					from="6"
					weight="0.167322898629372"/>
				<Con
					from="7"
					weight="1.36234354013525"/>
			</Neuron>
			<Neuron
				id="10"
				bias="-0.413250409241325">
				<Con
					from="0"
					weight="-0.0178186362880915"/>
				<Con
					from="1"
					weight="0.179296280639353"/>
				<Con
					from="2"
					weight="-0.41615849977404"/>
				<Con
					from="3"
					weight="-0.281478463506155"/>
				<Con
					from="4"
					weight="0.198585250295662"/>
				<Con
					from="5"
					weight="0.250614612482613"/>
				<Con
					from="6"
					weight="-0.249929322891288"/>
				<Con
					from="7"
					weight="-0.631863768487314"/>
			</Neuron>
			<Neuron
				id="11"
				bias="0.125185445279167">
				<Con
					from="0"
					weight="-0.0349925508585408"/>
				<Con
					from="1"
					weight="0.52015354831743"/>
				<Con
					from="2"
					weight="0.489824795007128"/>
				<Con
					from="3"
					weight="0.326123077769299"/>
				<Con
					from="4"
					weight="-0.413498589442788"/>
				<Con
					from="5"
					weight="-0.131490646155752"/>
				<Con
					from="6"
					weight="-0.180146343947792"/>
				<Con
					from="7"
					weight="-0.263113938127349"/>
			</Neuron>
			<Neuron
				id="12"
				bias="0.0798368051104475">
				<Con
					from="0"
					weight="0.374577039082009"/>
				<Con
					from="1"
					weight="0.134717576193546"/>
				<Con
					from="2"
					weight="-0.311610517824904"/>
				<Con
					from="3"
					weight="0.186952649589172"/>
				<Con
					from="4"
					weight="-0.213610460151725"/>
				<Con
					from="5"
					weight="0.0972773056757849"/>
				<Con
					from="6"
					weight="0.155030870401533"/>
				<Con
					from="7"
					weight="1.35107285882734"/>
			</Neuron>
			<Neuron
				id="13"
				bias="-0.412410525973474">
				<Con
					from="0"
					weight="0.0468991784890131"/>
				<Con
					from="1"
					weight="-0.416615512595282"/>
				<Con
					from="2"
					weight="0.297597596454553"/>
				<Con
					from="3"
					weight="-0.163051402112051"/>
				<Con
					from="4"
					weight="-0.437239668141151"/>
				<Con
					from="5"
					weight="-0.601112994807352"/>
				<Con
					from="6"
					weight="-0.0739818285889701"/>
				<Con
					from="7"
					weight="-0.224464918019132"/>
			</Neuron>
			<Neuron
				id="14"
				bias="0.283125194581721">
				<Con
					from="0"
					weight="-0.423110768510766"/>
				<Con
					from="1"
					weight="0.223481925155265"/>
				<Con
					from="2"
					weight="-0.145709520438861"/>
				<Con
					from="3"
					weight="0.344433422128214"/>
				<Con
					from="4"
					weight="-0.219278856850105"/>
				<Con
					from="5"
					weight="0.169506826933362"/>
				<Con
					from="6"
					weight="-0.12635690376384"/>
				<Con
					from="7"
					weight="-0.970326887437824"/>
			</Neuron>
			<Neuron
				id="15"
				bias="0.254059176295755">
				<Con
					from="0"
					weight="0.179348241946687"/>
				<Con
					from="1"
					weight="0.359838714471777"/>
				<Con
					from="2"
					weight="0.0620879767151191"/>
				<Con
					from="3"
					weight="-0.307657096071168"/>
				<Con
					from="4"
					weight="-0.366350796335983"/>
				<Con
					from="5"
					weight="0.125897010790871"/>
				<Con
					from="6"
					weight="-0.516243687219117"/>
				<Con
					from="7"
					weight="0.660812243979281"/>
			</Neuron>
		</NeuralLayer>
		<NeuralLayer
			numberOfNeurons="3">
			<Neuron
				id="16"
				bias="-0.278009151367687">
				<Con
					from="8"
					weight="0.280979960415889"/>
				<Con
					from="9"
					weight="0.236287950413653"/>
				<Con
					from="10"
					weight="0.0329713783101491"/>
				<Con
					from="11"
					weight="-0.0951550577335478"/>
				<Con
					from="12"
					weight="0.745714825829193"/>
				<Con
					from="13"
					weight="-0.306022307925867"/>
				<Con
					from="14"
					weight="-0.453590089573164"/>
				<Con
					from="15"
					weight="0.605864096287647"/>
			</Neuron>
			<Neuron
				id="17"
				bias="-0.181352738477288">
				<Con
					from="8"
					weight="-0.281775505311393"/>
				<Con
					from="9"
					weight="0.771558369035269"/>
				<Con
					from="10"
					weight="-0.462440276362596"/>
				<Con
					from="11"
					weight="-0.560489357810888"/>
				<Con
					from="12"
					weight="1.11167612541093"/>
				<Con
					from="13"
					weight="0.217438805785158"/>
				<Con
					from="14"
					weight="-0.620534551951495"/>
				<Con
					from="15"
					weight="0.188198082081134"/>
			</Neuron>
			<Neuron
				id="18"
				bias="0.269824014863734">
				<Con
					from="8"
					weight="0.381177309074082"/>
				<Con
					from="9"
					weight="-1.07247403940686"/>
				<Con
					from="10"
					weight="0.568417855769917"/>
				<Con
					from="11"
					weight="0.113371070963566"/>
				<Con
					from="12"
					weight="-0.813068523878886"/>
				<Con
					from="13"
					weight="0.663784335846275"/>
				<Con
					from="14"
					weight="1.09300234967044"/>
				<Con
					from="15"
					weight="-0.560146508824824"/>
			</Neuron>
		</NeuralLayer>
		<NeuralLayer
			numberOfNeurons="1"
			activationFunction="identity">
			<Neuron
				id="19"
				bias="-0.0387785419844283">
				<Con
					from="16"
					weight="0.831288587269389"/>
				<Con
					from="17"
					weight="1.93690399653014"/>
				<Con
					from="18"
					weight="-2.23923904358143"/>
			</Neuron>
		</NeuralLayer>
		<NeuralOutputs>
			<NeuralOutput
				outputNeuron="19">
				<DerivedField
					optype="continuous"
					dataType="double">
					<FieldRef
						field="revenueNorm"/>
				</DerivedField>
			</NeuralOutput>
		</NeuralOutputs>
	</NeuralNetwork>
</PMML>